restutil/__init__.py
restutil/common.py
restutil/decorators.py
restutil/dictionary.py
restutil/encoder.py
restutil/files.py
restutil/logger.py
restutil/operations.py
restutil/result.py
restutil/fastapi/__init__.py
restutil/fastapi/openapi.py
restutil-1.0.15.dist-info/LICENSE
restutil-1.0.15.dist-info/METADATA
restutil-1.0.15.dist-info/WHEEL
restutil-1.0.15.dist-info/top_level.txt
restutil-1.0.15.dist-info/RECORD
