Metadata-Version: 2.1
Name: restutil
Version: 1.0.15
Summary: Rest util and common tools
Home-page: https://github.com/adions025/restutil
Download-URL: https://github.com/adions025/restutil
Author: Adonis Gonzalez Godoy
Author-email: adions025@gmail.com
Keywords: Restfull,Rest,Util,Tools, Logger
Classifier: Programming Language :: Python :: 3.6
Classifier: Programming Language :: Python :: 3.7
Classifier: Programming Language :: Python :: 3.8
Classifier: Programming Language :: Python :: 3.9
Classifier: Programming Language :: Python :: 3.10
Classifier: Programming Language :: Python :: 3.11
License-File: LICENSE
